crocodile/__init__.py
crocodile/cli.py
crocodile/crocodile.py
crocodile/feature.py
crocodile/fetchers.py
crocodile/ml.py
crocodile/mongo.py
crocodile/processors.py
crocodile/result_fetcher.py
crocodile/typing.py
crocodile/utils.py
crocodile/models/default.h5
crocodile_linker-0.1.1.dist-info/licenses/LICENSE
crocodile_linker-0.1.1.dist-info/METADATA
crocodile_linker-0.1.1.dist-info/WHEEL
crocodile_linker-0.1.1.dist-info/top_level.txt
crocodile_linker-0.1.1.dist-info/RECORD
