Metadata-Version: 2.4
Name: crocodile-linker
Version: 0.1.1
Summary: A package for entity linking using LionLinker.
Author-email: Roberto Avogadro <roberto.avogadro@sintef.no>, Federico Belotti <belo.fede@outlook.com>
License: MIT
Project-URL: Homepage, https://github.com/enRichMyData/crocodile
Classifier: Programming Language :: Python :: 3
Classifier: License :: OSI Approved :: MIT License
Classifier: Operating System :: OS Independent
Requires-Python: >=3.9
License-File: LICENSE
Requires-Dist: pymongo==4.11.0
Requires-Dist: nltk==3.9.1
Requires-Dist: aiohttp==3.11.11
Requires-Dist: numpy<2.0
Requires-Dist: pandas>=2.0
Requires-Dist: python-dotenv==1.0.1
Requires-Dist: tensorflow==2.18.0
Requires-Dist: column-classifier
Requires-Dist: jsonargparse==4.37.0
Provides-Extra: app
Requires-Dist: fastapi==0.115; extra == "app"
Requires-Dist: pydantic<3; extra == "app"
Requires-Dist: pydantic-settings==2.8.1; extra == "app"
Requires-Dist: uvicorn==0.34; extra == "app"
Requires-Dist: python-multipart==0.0.20; extra == "app"
Requires-Dist: python-jose==3.4.0; extra == "app"
Requires-Dist: elasticsearch==8.9.0; extra == "app"
Provides-Extra: dev
Requires-Dist: flake8==4.0.1; extra == "dev"
Requires-Dist: black==21.12b0; extra == "dev"
Requires-Dist: isort==5.10.0; extra == "dev"
Requires-Dist: mypy==0.910; extra == "dev"
Requires-Dist: pre-commit==4.1.0; extra == "dev"
Dynamic: license-file
